mooquant_mercadobitcoin/__init__.py
mooquant_mercadobitcoin/api.py
mooquant_mercadobitcoin/broker.py
mooquant_mercadobitcoin/common.py
mooquant_mercadobitcoin/livefeed.py
mooquant_mercadobitcoin-0.1.0.dist-info/METADATA
mooquant_mercadobitcoin-0.1.0.dist-info/RECORD
mooquant_mercadobitcoin-0.1.0.dist-info/WHEEL
mooquant_mercadobitcoin-0.1.0.dist-info/entry_points.txt
mooquant_mercadobitcoin-0.1.0.dist-info/top_level.txt
